desktop_drive/__init__.py
desktop_drive/application.py
desktop_drive/client_id.json
desktop_drive/drive.py
desktop_drive/filesystem.py
desktop_drive/local.py
desktop_drive/main.py
desktop_drive/path.py
desktop_drive/system.py
desktop_drive/terminal.py
desktop_drive-0.3a1.dist-info/DESCRIPTION.rst
desktop_drive-0.3a1.dist-info/METADATA
desktop_drive-0.3a1.dist-info/RECORD
desktop_drive-0.3a1.dist-info/WHEEL
desktop_drive-0.3a1.dist-info/entry_points.txt
desktop_drive-0.3a1.dist-info/metadata.json
desktop_drive-0.3a1.dist-info/top_level.txt
